{
    "1418fb94e984-a8d6d622af696e5c9c4aca23515cf34a@airbnb.com": {
        "updated_at": "2025-05-25 18:52:08",
        "raw": "Hoppa till inneh\u00e5ll\r\nIdag\r\nKalender\r\nAnnonser\r\nMeddelanden\r\n\r\nMeny\r\n\r\n\r\n\r\nBokningsinformation\r\nSkriv ut\r\nBekr\u00e4ftad\r\nElizabeth Madeiros\r\nProfilbilden f\u00f6r Elizabeth\r\nTidigare annons \u00b7 Villa med pool\r\n27 juni\u2009\u2013\u20095 juli (8 n\u00e4tter)\r\n5 g\u00e4ster \u00b7 33 594,01 kr\r\nOm Elizabeth\r\nIdentitet verifierad\r\nInga resor \u00e4nnu\r\nBlev medlem p\u00e5 Airbnb 2019\r\nVisa profil\r\nSkicka eller beg\u00e4r pengar\r\nSkicka meddelande\r\nRing\r\nTelefon: \u202a+1 441-505-8931\u202c\r\nBokningsinformation\r\nG\u00e4ster\r\n3 vuxna, 2 barn\r\nVisa\r\nIncheckning\r\nfre 27 juni 2025\r\nUtcheckning\r\nl\u00f6r 5 juli 2025\r\nBokningsdatum\r\nfre 21 feb. 2025\r\nBekr\u00e4ftelsekod\r\nHMZNTZ5NMT\r\nAvbokningspolicy\r\nM\u00e5ttlig\r\nVisa kalender\r\nG\u00e4st betalade\r\n4 204,13 kr x 8 n\u00e4tter\r\n33 633,00 kr\r\nSt\u00e4davgift\r\n1 000,00 kr\r\nServiceavgift f\u00f6r g\u00e4ster\r\n5 284,60 kr\r\nTotalt (SEK)\r\n39 917,60 kr\r\nUtbetalning f\u00f6r v\u00e4rdar\r\nRumsavgift f\u00f6r 8 n\u00e4tter\r\n37 370,00 kr\r\nVisa \u00f6versikt\r\nSt\u00e4davgift\r\n1 000,00 kr\r\nJustering av pris per natt\r\n\u22123 737,00 kr\r\nVisa \u00f6versikt\r\nServiceavgift f\u00f6r v\u00e4rdar (3.0 %)\r\n\u22121 038,99 kr\r\nTotalt (SEK)\r\n33 594,01 kr\r\nMomsfaktura *2612\r\nTransaktionshistorik\r\nKalenderanteckning\r\nL\u00e4gg till en privat p\u00e5minnelse f\u00f6r dessa datum som bara du kan se\r\nSkriv en anteckning\r\nSpara\r\nSkydd fr\u00e5n b\u00f6rjan till slut, varje g\u00e5ng du \u00e4r v\u00e4rd.\r\nL\u00e4s mer\r\nSt\u00f6d\r\n\u00c4ndra bokning\r\nAnm\u00e4l denna g\u00e4st\r\nBes\u00f6k hj\u00e4lpcentret\r\nAnnullera bokning\r\nOm du avbokar kan du komma att debiteras en avgift och dessa datum kan komma att blockeras. Om du avbokar f\u00f6r ofta kan det leda till att du inte \u00e4r ber\u00e4ttigad till Superhost-status och att din annons tillf\u00e4lligt kan st\u00e4ngas av eller tas bort. \r\n\r\nL\u00e4s mer om att avboka\r\nVanliga fr\u00e5gor\r\n\u00c4ndra en bokning av ett boende som v\u00e4rd\r\nDu kan skicka en \u00e4ndringsf\u00f6rfr\u00e5gan till din g\u00e4st. Om g\u00e4sten godk\u00e4nner s\u00e5 uppdateras bokningen.\r\nL\u00e4s vidare\r\nV\u00e4rdavbokningspolicy f\u00f6r boenden\r\nEffective date: October 9, 2023\r\nL\u00e4s vidare\r\nD\u00e5 f\u00e5r du din utbetalning\r\nVi skickar vanligtvis utbetalningar ungef\u00e4r 24 timmar efter det att g\u00e4sten checkar in f\u00f6r vistelser i boendet och efter det att en tj\u00e4nst eller upplevelse har slutf\u00f6rts. N\u00e4r du f\u00e5r din utbetalning kan variera beroende p\u00e5 flera faktorer.\r\nL\u00e4s vidare\r\nVisa fler \u00e4mnen\r\n",
        "name": "Elizabeth Madeiros",
        "guests": "5 g\u00e4ster",
        "dates": "27 juni\u2009\u2013\u20095 juli",
        "duration": "8 n\u00e4tter",
        "price": 33594.01,
        "rating": "?",
        "language": "",
        "living": "",
        "membertime": "2019",
        "host": ""
    },
    "1418fb94e984-9c16ea090ae18c807c1bdaec78f22487@airbnb.com": {
        "updated_at": "2025-05-25 18:49:32",
        "raw": "Hoppa till inneh\u00e5ll\r\nIdag\r\nKalender\r\nAnnonser\r\nMeddelanden\r\n\r\nMeny\r\n\r\n\r\n\r\nBokningsinformation\r\nSkriv ut\r\nBekr\u00e4ftad\r\nCalle Emander\r\nProfilbilden f\u00f6r Calle\r\nMysigt boende med egen tomt\r\n13\u201315 juni (2 n\u00e4tter)\r\n4 g\u00e4ster \u00b7 1 949,70 kr\r\nOm Calle\r\n5,0 i betyg fr\u00e5n 5 omd\u00f6men\r\nIdentitet verifierad\r\nBlev medlem p\u00e5 Airbnb 2020\r\nBor i Stockholms l\u00e4n, Sverige\r\nVisa profil\r\nSkicka eller beg\u00e4r pengar\r\nSkicka meddelande\r\nRing\r\nTelefon: \u202a+46 73 933 23 60\u202c\r\nBokningsinformation\r\nG\u00e4ster\r\n4 vuxna\r\nVisa\r\nIncheckning\r\nfre 13 juni 2025\r\nUtcheckning\r\ns\u00f6n 15 juni 2025\r\nBokningsdatum\r\nfre 23 maj 2025\r\nBekr\u00e4ftelsekod\r\nHMEE2T5JPD\r\nAvbokningspolicy\r\nFlexibel\r\nVisa kalender\r\nG\u00e4st betalade\r\n1 005,00 kr x 2 n\u00e4tter\r\n2 010,00 kr\r\nServiceavgift f\u00f6r g\u00e4ster\r\n354,71 kr\r\nTotalt (SEK)\r\n2 364,71 kr\r\nUtbetalning f\u00f6r v\u00e4rdar\r\nRumsavgift f\u00f6r 2 n\u00e4tter\r\n2 010,00 kr\r\nVisa \u00f6versikt\r\nServiceavgift f\u00f6r v\u00e4rdar (3.0 %)\r\n\u221260,30 kr\r\nTotalt (SEK)\r\n1 949,70 kr\r\nMomsfaktura *5064\r\nTransaktionshistorik\r\nKalenderanteckning\r\nL\u00e4gg till en privat p\u00e5minnelse f\u00f6r dessa datum som bara du kan se\r\nSkriv en anteckning\r\nSpara\r\nSkydd fr\u00e5n b\u00f6rjan till slut, varje g\u00e5ng du \u00e4r v\u00e4rd.\r\nL\u00e4s mer\r\nSt\u00f6d\r\n\u00c4ndra bokning\r\nAnm\u00e4l denna g\u00e4st\r\nBes\u00f6k hj\u00e4lpcentret\r\nAnnullera bokning\r\nOm du avbokar kan du komma att debiteras en avgift och dessa datum kan komma att blockeras. Om du avbokar f\u00f6r ofta kan det leda till att du inte \u00e4r ber\u00e4ttigad till Superhost-status och att din annons tillf\u00e4lligt kan st\u00e4ngas av eller tas bort. \r\n\r\nL\u00e4s mer om att avboka\r\nVanliga fr\u00e5gor\r\n\u00c4ndra en bokning av ett boende som v\u00e4rd\r\nDu kan skicka en \u00e4ndringsf\u00f6rfr\u00e5gan till din g\u00e4st. Om g\u00e4sten godk\u00e4nner s\u00e5 uppdateras bokningen.\r\nL\u00e4s vidare\r\nV\u00e4rdavbokningspolicy f\u00f6r boenden\r\nEffective date: October 9, 2023\r\nL\u00e4s vidare\r\nD\u00e5 f\u00e5r du din utbetalning\r\nVi skickar vanligtvis utbetalningar ungef\u00e4r 24 timmar efter det att g\u00e4sten checkar in f\u00f6r vistelser i boendet och efter det att en tj\u00e4nst eller upplevelse har slutf\u00f6rts. N\u00e4r du f\u00e5r din utbetalning kan variera beroende p\u00e5 flera faktorer.\r\nL\u00e4s vidare\r\nVisa fler \u00e4mnen\r\n",
        "name": "Calle Emander",
        "guests": "4 g\u00e4ster",
        "dates": "13\u201315 juni",
        "duration": "2 n\u00e4tter",
        "price": 1949.7,
        "rating": "5,0",
        "language": "",
        "living": "Stockholms l\u00e4n, Sverige",
        "membertime": "2020",
        "host": ""
    },
    "1418fb94e984-e3ed43074874ed8e32e1c95e590cc451@airbnb.com": {
        "updated_at": "2025-05-25 18:49:35",
        "raw": "Hoppa till inneh\u00e5ll\r\nIdag\r\nKalender\r\nAnnonser\r\nMeddelanden\r\n\r\nMeny\r\n\r\n\r\n\r\nBokningsinformation\r\nSkriv ut\r\nBekr\u00e4ftad\r\nJulia Min\u00f6\r\nProfilbilden f\u00f6r Julia\r\nStor villa med pool\r\n20\u201322 juni (2 n\u00e4tter)\r\n5 g\u00e4ster \u00b7 6 356,35 kr\r\nOm Julia\r\n5,0 i betyg fr\u00e5n 1 omd\u00f6me\r\nIdentitet verifierad\r\nBlev medlem p\u00e5 Airbnb 2013\r\nBor i Stockholm, Sverige\r\nVisa profil\r\nSkicka eller beg\u00e4r pengar\r\nSkicka meddelande\r\nRing\r\nTelefon: \u202a+46 70 743 06 04\u202c\r\nBokningsinformation\r\nG\u00e4ster\r\n5 vuxna\r\nVisa\r\nIncheckning\r\nfre 20 juni 2025\r\nUtcheckning\r\ns\u00f6n 22 juni 2025\r\nBokningsdatum\r\nons 7 maj 2025\r\nBekr\u00e4ftelsekod\r\nHMFTAMX5ET\r\nAvbokningspolicy\r\nFlexibel\r\nVisa kalender\r\nG\u00e4st betalade\r\nBoende\r\n4 604,00 kr\r\nSt\u00e4davgift\r\n2 000,00 kr\r\nServiceavgift f\u00f6r g\u00e4ster\r\n1 165,41 kr\r\nTotalt (SEK)\r\n7 769,41 kr\r\nUtbetalning f\u00f6r v\u00e4rdar\r\nTotalpris f\u00f6r vistelse\r\n4 604,00 kr\r\nSt\u00e4davgift\r\n2 000,00 kr\r\nServiceavgift f\u00f6r v\u00e4rdar (3.0 % + moms)\r\n\u2212247,65 kr\r\nTotalt (SEK)\r\n6 356,35 kr\r\nMomsfaktura *8134\r\nTransaktionshistorik\r\nKalenderanteckning\r\nL\u00e4gg till en privat p\u00e5minnelse f\u00f6r dessa datum som bara du kan se\r\nSkriv en anteckning\r\nSpara\r\nSkydd fr\u00e5n b\u00f6rjan till slut, varje g\u00e5ng du \u00e4r v\u00e4rd.\r\nL\u00e4s mer\r\nSt\u00f6d\r\n\u00c4ndra bokning\r\nAnm\u00e4l denna g\u00e4st\r\nBes\u00f6k hj\u00e4lpcentret\r\nAnnullera bokning\r\nOm du avbokar kan du komma att debiteras en avgift och dessa datum kan komma att blockeras. Om du avbokar f\u00f6r ofta kan det leda till att du inte \u00e4r ber\u00e4ttigad till Superhost-status och att din annons tillf\u00e4lligt kan st\u00e4ngas av eller tas bort. \r\n\r\nL\u00e4s mer om att avboka\r\nVanliga fr\u00e5gor\r\n\u00c4ndra en bokning av ett boende som v\u00e4rd\r\nDu kan skicka en \u00e4ndringsf\u00f6rfr\u00e5gan till din g\u00e4st. Om g\u00e4sten godk\u00e4nner s\u00e5 uppdateras bokningen.\r\nL\u00e4s vidare\r\nV\u00e4rdavbokningspolicy f\u00f6r boenden\r\nEffective date: October 9, 2023\r\nL\u00e4s vidare\r\nD\u00e5 f\u00e5r du din utbetalning\r\nVi skickar vanligtvis utbetalningar ungef\u00e4r 24 timmar efter det att g\u00e4sten checkar in f\u00f6r vistelser i boendet och efter det att en tj\u00e4nst eller upplevelse har slutf\u00f6rts. N\u00e4r du f\u00e5r din utbetalning kan variera beroende p\u00e5 flera faktorer.\r\nL\u00e4s vidare\r\nVisa fler \u00e4mnen\r\n",
        "name": "Julia Min\u00f6",
        "guests": "5 g\u00e4ster",
        "dates": "20\u201322 juni",
        "duration": "2 n\u00e4tter",
        "price": 6356.35,
        "rating": "5,0",
        "language": "",
        "living": "Stockholm, Sverige",
        "membertime": "2013",
        "host": ""
    },
    "1418fb94e984-482120268847638d19b1ec905e96eb38@airbnb.com": {
        "updated_at": "2025-05-25 18:49:38",
        "raw": "Hoppa till inneh\u00e5ll\r\nIdag\r\nKalender\r\nAnnonser\r\nMeddelanden\r\n\r\nMeny\r\n\r\n\r\n\r\nBokningsinformation\r\nSkriv ut\r\nBekr\u00e4ftad\r\nAnnika Rundb\u00e4ck\r\nProfilbilden f\u00f6r Annika\r\nMysigt boende med egen tomt\r\n22\u201329 juni (7 n\u00e4tter)\r\n2 g\u00e4ster \u00b7 7 185,76 kr\r\nOm Annika\r\n5,0 i betyg fr\u00e5n 1 omd\u00f6me\r\nIdentitet verifierad\r\nBlev medlem p\u00e5 Airbnb 2022\r\nVisa profil\r\nSkicka eller beg\u00e4r pengar\r\nSkicka meddelande\r\nRing\r\nTelefon: \u202a+46 72 303 00 73\u202c\r\nBokningsinformation\r\nG\u00e4ster\r\n2 vuxna\r\nVisa\r\nIncheckning\r\ns\u00f6n 22 juni 2025\r\nUtcheckning\r\ns\u00f6n 29 juni 2025\r\nBokningsdatum\r\nm\u00e5n 31 mars 2025\r\nBekr\u00e4ftelsekod\r\nHMMA5B9P83\r\nAvbokningspolicy\r\nFlexibel\r\nVisa kalender\r\nG\u00e4st betalade\r\n1 058,29 kr x 7 n\u00e4tter\r\n7 408,00 kr\r\nServiceavgift f\u00f6r g\u00e4ster\r\n1 307,30 kr\r\nTotalt (SEK)\r\n8 715,30 kr\r\nUtbetalning f\u00f6r v\u00e4rdar\r\nRumsavgift f\u00f6r 7 n\u00e4tter\r\n9 260,00 kr\r\nVisa \u00f6versikt\r\nJustering av pris per natt\r\n\u22121 852,00 kr\r\nVisa \u00f6versikt\r\nServiceavgift f\u00f6r v\u00e4rdar (3.0 %)\r\n\u2212222,24 kr\r\nTotalt (SEK)\r\n7 185,76 kr\r\nMomsfaktura *8740\r\nTransaktionshistorik\r\nKalenderanteckning\r\nL\u00e4gg till en privat p\u00e5minnelse f\u00f6r dessa datum som bara du kan se\r\nSkriv en anteckning\r\nSpara\r\nSkydd fr\u00e5n b\u00f6rjan till slut, varje g\u00e5ng du \u00e4r v\u00e4rd.\r\nL\u00e4s mer\r\nSt\u00f6d\r\n\u00c4ndra bokning\r\nAnm\u00e4l denna g\u00e4st\r\nBes\u00f6k hj\u00e4lpcentret\r\nAnnullera bokning\r\nOm du avbokar kan du komma att debiteras en avgift och dessa datum kan komma att blockeras. Om du avbokar f\u00f6r ofta kan det leda till att du inte \u00e4r ber\u00e4ttigad till Superhost-status och att din annons tillf\u00e4lligt kan st\u00e4ngas av eller tas bort. \r\n\r\nL\u00e4s mer om att avboka\r\nVanliga fr\u00e5gor\r\n\u00c4ndra en bokning av ett boende som v\u00e4rd\r\nDu kan skicka en \u00e4ndringsf\u00f6rfr\u00e5gan till din g\u00e4st. Om g\u00e4sten godk\u00e4nner s\u00e5 uppdateras bokningen.\r\nL\u00e4s vidare\r\nV\u00e4rdavbokningspolicy f\u00f6r boenden\r\nEffective date: October 9, 2023\r\nL\u00e4s vidare\r\nD\u00e5 f\u00e5r du din utbetalning\r\nVi skickar vanligtvis utbetalningar ungef\u00e4r 24 timmar efter det att g\u00e4sten checkar in f\u00f6r vistelser i boendet och efter det att en tj\u00e4nst eller upplevelse har slutf\u00f6rts. N\u00e4r du f\u00e5r din utbetalning kan variera beroende p\u00e5 flera faktorer.\r\nL\u00e4s vidare\r\nVisa fler \u00e4mnen\r\n",
        "name": "Annika Rundb\u00e4ck",
        "guests": "2 g\u00e4ster",
        "dates": "22\u201329 juni",
        "duration": "7 n\u00e4tter",
        "price": 7185.76,
        "rating": "5,0",
        "language": "",
        "living": "",
        "membertime": "2022",
        "host": ""
    },
    "1418fb94e984-1451ed72a9eaa40ad06e56b4187ea99f@airbnb.com": {
        "updated_at": "2025-05-25 18:52:51",
        "raw": "Hoppa till inneh\u00e5ll\r\nIdag\r\nKalender\r\nAnnonser\r\nMeddelanden\r\n\r\nMeny\r\n\r\n\r\n\r\nBokningsinformation\r\nSkriv ut\r\nBekr\u00e4ftad\r\nCharlotte Liljestrand\r\nProfilbilden f\u00f6r Charlotte\r\nStor villa med pool\r\n9\u201313 juli (4 n\u00e4tter)\r\n6 g\u00e4ster \u00b7 16 920,75 kr\r\nOm Charlotte\r\n5,0 i betyg fr\u00e5n 4 omd\u00f6men\r\nIdentitet verifierad\r\nBlev medlem p\u00e5 Airbnb 2019\r\nBor i Karlstad, Sverige\r\nTalar engelska och svenska\r\nVisa profil\r\nSkicka eller beg\u00e4r pengar\r\nSkicka meddelande\r\nRing\r\nTelefon: \u202a+46 70 344 04 14\u202c\r\nBokningsinformation\r\nG\u00e4ster\r\n5 vuxna, 1 barn\r\nVisa\r\nIncheckning\r\nons 9 juli 2025\r\nUtcheckning\r\ns\u00f6n 13 juli 2025\r\nBokningsdatum\r\ntis 1 apr. 2025\r\nBekr\u00e4ftelsekod\r\nHMY8ZPHTFQ\r\nAvbokningspolicy\r\nFlexibel\r\nVisa kalender\r\nG\u00e4st betalade\r\n4 395,00 kr x 4 n\u00e4tter\r\n17 580,00 kr\r\nServiceavgift f\u00f6r g\u00e4ster\r\n3 102,36 kr\r\nTotalt (SEK)\r\n20 682,36 kr\r\nUtbetalning f\u00f6r v\u00e4rdar\r\nRumsavgift f\u00f6r 4 n\u00e4tter\r\n17 580,00 kr\r\nVisa \u00f6versikt\r\nServiceavgift f\u00f6r v\u00e4rdar (3.0 % + moms)\r\n\u2212659,25 kr\r\nTotalt (SEK)\r\n16 920,75 kr\r\nMomsfaktura *6216\r\nTransaktionshistorik\r\nKalenderanteckning\r\nL\u00e4gg till en privat p\u00e5minnelse f\u00f6r dessa datum som bara du kan se\r\nSkriv en anteckning\r\nSpara\r\nSkydd fr\u00e5n b\u00f6rjan till slut, varje g\u00e5ng du \u00e4r v\u00e4rd.\r\nL\u00e4s mer\r\nSt\u00f6d\r\n\u00c4ndra bokning\r\nAnm\u00e4l denna g\u00e4st\r\nBes\u00f6k hj\u00e4lpcentret\r\nAnnullera bokning\r\nOm du avbokar kan du komma att debiteras en avgift och dessa datum kan komma att blockeras. Om du avbokar f\u00f6r ofta kan det leda till att du inte \u00e4r ber\u00e4ttigad till Superhost-status och att din annons tillf\u00e4lligt kan st\u00e4ngas av eller tas bort. \r\n\r\nL\u00e4s mer om att avboka\r\nVanliga fr\u00e5gor\r\n\u00c4ndra en bokning av ett boende som v\u00e4rd\r\nDu kan skicka en \u00e4ndringsf\u00f6rfr\u00e5gan till din g\u00e4st. Om g\u00e4sten godk\u00e4nner s\u00e5 uppdateras bokningen.\r\nL\u00e4s vidare\r\nV\u00e4rdavbokningspolicy f\u00f6r boenden\r\nEffective date: October 9, 2023\r\nL\u00e4s vidare\r\nD\u00e5 f\u00e5r du din utbetalning\r\nVi skickar vanligtvis utbetalningar ungef\u00e4r 24 timmar efter det att g\u00e4sten checkar in f\u00f6r vistelser i boendet och efter det att en tj\u00e4nst eller upplevelse har slutf\u00f6rts. N\u00e4r du f\u00e5r din utbetalning kan variera beroende p\u00e5 flera faktorer.\r\nL\u00e4s vidare\r\nVisa fler \u00e4mnen\r\n",
        "name": "Charlotte Liljestrand",
        "guests": "6 g\u00e4ster",
        "dates": "9\u201313 juli",
        "duration": "4 n\u00e4tter",
        "price": 16920.75,
        "rating": "5,0",
        "language": "engelska och svenska",
        "living": "Karlstad, Sverige",
        "membertime": "2019",
        "host": ""
    },
    "1418fb94e984-10859af54997170e6a8dc8b0dba95c62@airbnb.com": {
        "updated_at": "2025-06-28 13:30:37",
        "raw": "Mysigt boende med egen tomt\r\n29 juni\u2009\u2013\u20092 juli (3 n\u00e4tter)\r\n4 g\u00e4ster \u00b7 3 395,00 kr",
        "guests": "4 g\u00e4ster",
        "price": 3395,
        "rating": "?",
        "language": "",
        "living": "",
        "membertime": "",
        "host": ""
    },
    "1418fb94e984-af8b1926703782b908b4a8a271aedb8f@airbnb.com": {
        "updated_at": "2025-05-25 18:53:20",
        "raw": "Hoppa till inneh\u00e5ll\r\nIdag\r\nKalender\r\nAnnonser\r\nMeddelanden\r\n\r\nMeny\r\n\r\n\r\n\r\nBokningsinformation\r\nSkriv ut\r\nBekr\u00e4ftad\r\nAnton Lymer\r\nProfilbilden f\u00f6r Anton\r\nStor villa med pool\r\n14\u201321 juli (7 n\u00e4tter)\r\n4 g\u00e4ster \u00b7 14 009,05 kr\r\nOm Anton\r\nIdentitet verifierad\r\nInga resor \u00e4nnu\r\nBlev medlem p\u00e5 Airbnb 2025\r\nVisa profil\r\nSkicka eller beg\u00e4r pengar\r\nSkicka meddelande\r\nRing\r\nTelefon: \u202a+46 73 157 60 14\u202c\r\nBokningsinformation\r\nG\u00e4ster\r\n2 vuxna, 2 barn\r\nVisa\r\nIncheckning\r\nm\u00e5n 14 juli 2025\r\nUtcheckning\r\nm\u00e5n 21 juli 2025\r\nBokningsdatum\r\nfre 11 apr. 2025\r\nBekr\u00e4ftelsekod\r\nHM33S9XY2Y\r\nAvbokningspolicy\r\nFlexibel\r\nVisa kalender\r\nG\u00e4st betalade\r\n2 079,26 kr x 7 n\u00e4tter\r\n14 554,80 kr\r\nServiceavgift f\u00f6r g\u00e4ster\r\n2 776,08 kr\r\nTotalt (SEK)\r\n17 330,88 kr\r\nUtbetalning f\u00f6r v\u00e4rdar\r\nRumsavgift f\u00f6r 7 n\u00e4tter\r\n16 172,00 kr\r\nVisa \u00f6versikt\r\nJustering av pris per natt\r\n\u22121 617,20 kr\r\nVisa \u00f6versikt\r\nServiceavgift f\u00f6r v\u00e4rdar (3.0 % + moms)\r\n\u2212545,75 kr\r\nTotalt (SEK)\r\n14 009,05 kr\r\nMomsfaktura *0850\r\nTransaktionshistorik\r\nKalenderanteckning\r\nL\u00e4gg till en privat p\u00e5minnelse f\u00f6r dessa datum som bara du kan se\r\nSkriv en anteckning\r\nSpara\r\nSkydd fr\u00e5n b\u00f6rjan till slut, varje g\u00e5ng du \u00e4r v\u00e4rd.\r\nL\u00e4s mer\r\nSt\u00f6d\r\n\u00c4ndra bokning\r\nAnm\u00e4l denna g\u00e4st\r\nBes\u00f6k hj\u00e4lpcentret\r\nAnnullera bokning\r\nOm du avbokar kan du komma att debiteras en avgift och dessa datum kan komma att blockeras. Om du avbokar f\u00f6r ofta kan det leda till att du inte \u00e4r ber\u00e4ttigad till Superhost-status och att din annons tillf\u00e4lligt kan st\u00e4ngas av eller tas bort. \r\n\r\nL\u00e4s mer om att avboka\r\nVanliga fr\u00e5gor\r\n\u00c4ndra en bokning av ett boende som v\u00e4rd\r\nDu kan skicka en \u00e4ndringsf\u00f6rfr\u00e5gan till din g\u00e4st. Om g\u00e4sten godk\u00e4nner s\u00e5 uppdateras bokningen.\r\nL\u00e4s vidare\r\nV\u00e4rdavbokningspolicy f\u00f6r boenden\r\nEffective date: October 9, 2023\r\nL\u00e4s vidare\r\nD\u00e5 f\u00e5r du din utbetalning\r\nVi skickar vanligtvis utbetalningar ungef\u00e4r 24 timmar efter det att g\u00e4sten checkar in f\u00f6r vistelser i boendet och efter det att en tj\u00e4nst eller upplevelse har slutf\u00f6rts. N\u00e4r du f\u00e5r din utbetalning kan variera beroende p\u00e5 flera faktorer.\r\nL\u00e4s vidare\r\nVisa fler \u00e4mnen\r\n",
        "name": "Anton Lymer",
        "guests": "4 g\u00e4ster",
        "dates": "14\u201321 juli",
        "duration": "7 n\u00e4tter",
        "price": 14009.05,
        "rating": "?",
        "language": "",
        "living": "",
        "membertime": "2025",
        "host": ""
    },
    "1418fb94e984-1b1c6b88931d05d533af268c10599d7e@airbnb.com": {
        "updated_at": "2025-05-25 18:51:35",
        "raw": "Hoppa till inneh\u00e5ll\r\nIdag\r\nKalender\r\nAnnonser\r\nMeddelanden\r\n\r\nMeny\r\n\r\n\r\n\r\nBokningsinformation\r\nSkriv ut\r\nBekr\u00e4ftad\r\nJelmer Keijts\r\nProfilbilden f\u00f6r Jelmer\r\nMysigt boende med egen tomt\r\n12\u201316 juli (4 n\u00e4tter)\r\n3 g\u00e4ster \u00b7 5 917,00 kr\r\nOm Jelmer\r\n2 omd\u00f6men\r\nIdentitet verifierad\r\nBlev medlem p\u00e5 Airbnb 2017\r\nBor i Haag, Nederl\u00e4nderna\r\nTalar engelska och nederl\u00e4ndska\r\nVisa profil\r\nSkicka eller beg\u00e4r pengar\r\nSkicka meddelande\r\nRing\r\nTelefon: \u202a+31 6 25263210\u202c\r\nBokningsinformation\r\nG\u00e4ster\r\n2 vuxna, 1 barn\r\nVisa\r\nIncheckning\r\nl\u00f6r 12 juli 2025\r\nUtcheckning\r\nons 16 juli 2025\r\nBokningsdatum\r\nfre 11 apr. 2025\r\nBekr\u00e4ftelsekod\r\nHM2QDD4QTB\r\nAvbokningspolicy\r\nFlexibel\r\nVisa kalender\r\nG\u00e4st betalade\r\n1 525,00 kr x 4 n\u00e4tter\r\n6 100,00 kr\r\nServiceavgift f\u00f6r g\u00e4ster\r\n1 126,25 kr\r\nTotalt (SEK)\r\n7 226,25 kr\r\nUtbetalning f\u00f6r v\u00e4rdar\r\nRumsavgift f\u00f6r 4 n\u00e4tter\r\n6 100,00 kr\r\nVisa \u00f6versikt\r\nServiceavgift f\u00f6r v\u00e4rdar (3.0 %)\r\n\u2212183,00 kr\r\nTotalt (SEK)\r\n5 917,00 kr\r\nMomsfaktura *6434\r\nTransaktionshistorik\r\nKalenderanteckning\r\nL\u00e4gg till en privat p\u00e5minnelse f\u00f6r dessa datum som bara du kan se\r\nSkriv en anteckning\r\nSpara\r\nSkydd fr\u00e5n b\u00f6rjan till slut, varje g\u00e5ng du \u00e4r v\u00e4rd.\r\nL\u00e4s mer\r\nSt\u00f6d\r\n\u00c4ndra bokning\r\nAnm\u00e4l denna g\u00e4st\r\nBes\u00f6k hj\u00e4lpcentret\r\nAnnullera bokning\r\nOm du avbokar kan du komma att debiteras en avgift och dessa datum kan komma att blockeras. Om du avbokar f\u00f6r ofta kan det leda till att du inte \u00e4r ber\u00e4ttigad till Superhost-status och att din annons tillf\u00e4lligt kan st\u00e4ngas av eller tas bort. \r\n\r\nL\u00e4s mer om att avboka\r\nVanliga fr\u00e5gor\r\n\u00c4ndra en bokning av ett boende som v\u00e4rd\r\nDu kan skicka en \u00e4ndringsf\u00f6rfr\u00e5gan till din g\u00e4st. Om g\u00e4sten godk\u00e4nner s\u00e5 uppdateras bokningen.\r\nL\u00e4s vidare\r\nV\u00e4rdavbokningspolicy f\u00f6r boenden\r\nEffective date: October 9, 2023\r\nL\u00e4s vidare\r\nD\u00e5 f\u00e5r du din utbetalning\r\nVi skickar vanligtvis utbetalningar ungef\u00e4r 24 timmar efter det att g\u00e4sten checkar in f\u00f6r vistelser i boendet och efter det att en tj\u00e4nst eller upplevelse har slutf\u00f6rts. N\u00e4r du f\u00e5r din utbetalning kan variera beroende p\u00e5 flera faktorer.\r\nL\u00e4s vidare\r\nVisa fler \u00e4mnen\r\n",
        "name": "Jelmer Keijts",
        "guests": "3 g\u00e4ster",
        "dates": "12\u201316 juli",
        "duration": "4 n\u00e4tter",
        "price": 5917,
        "rating": "?",
        "language": "engelska och nederl\u00e4ndska",
        "living": "Haag, Nederl\u00e4nderna",
        "membertime": "2017",
        "host": ""
    },
    "1418fb94e984-ca0599f1616247910da25b116c6ad05f@airbnb.com": {
        "updated_at": "2025-05-25 18:26:59",
        "raw": "Hoppa till inneh\u00e5ll\r\nIdag\r\nKalender\r\nAnnonser\r\nMeddelanden\r\n\r\nMeny\r\n\r\n\r\n\r\nBokningsinformation\r\nSkriv ut\r\nBekr\u00e4ftad\r\nCharlotte S\u00f6derberg\r\nProfilbilden f\u00f6r Charlotte\r\nMysigt boende med egen tomt\r\n16\u201318 juli (2 n\u00e4tter)\r\n4 g\u00e4ster \u00b7 1 940,00 kr\r\nOm Charlotte\r\nIdentitet verifierad\r\nInga resor \u00e4nnu\r\nBlev medlem p\u00e5 Airbnb 2025\r\nVisa profil\r\nSkicka eller beg\u00e4r pengar\r\nSkicka meddelande\r\nRing\r\nTelefon: \u202a+46 70 293 77 27\u202c\r\nBokningsinformation\r\nG\u00e4ster\r\n4 vuxna\r\nVisa\r\nIncheckning\r\nons 16 juli 2025\r\nUtcheckning\r\nfre 18 juli 2025\r\nBokningsdatum\r\nm\u00e5n 14 apr. 2025\r\nBekr\u00e4ftelsekod\r\nHMCBDDWP5A\r\nAvbokningspolicy\r\nFlexibel\r\nVisa kalender\r\nG\u00e4st betalade\r\n1 000,00 kr x 2 n\u00e4tter\r\n2 000,00 kr\r\nServiceavgift f\u00f6r g\u00e4ster\r\n352,94 kr\r\nTotalt (SEK)\r\n2 352,94 kr\r\nUtbetalning f\u00f6r v\u00e4rdar\r\nRumsavgift f\u00f6r 2 n\u00e4tter\r\n2 000,00 kr\r\nVisa \u00f6versikt\r\nServiceavgift f\u00f6r v\u00e4rdar (3.0 %)\r\n\u221260,00 kr\r\nTotalt (SEK)\r\n1 940,00 kr\r\nMomsfaktura *2032\r\nTransaktionshistorik\r\nKalenderanteckning\r\nL\u00e4gg till en privat p\u00e5minnelse f\u00f6r dessa datum som bara du kan se\r\nSkriv en anteckning\r\nSpara\r\nSkydd fr\u00e5n b\u00f6rjan till slut, varje g\u00e5ng du \u00e4r v\u00e4rd.\r\nL\u00e4s mer\r\nSt\u00f6d\r\n\u00c4ndra bokning\r\nAnm\u00e4l denna g\u00e4st\r\nBes\u00f6k hj\u00e4lpcentret\r\nAnnullera bokning\r\nOm du avbokar kan du komma att debiteras en avgift och dessa datum kan komma att blockeras. Om du avbokar f\u00f6r ofta kan det leda till att du inte \u00e4r ber\u00e4ttigad till Superhost-status och att din annons tillf\u00e4lligt kan st\u00e4ngas av eller tas bort. \r\n\r\nL\u00e4s mer om att avboka\r\nVanliga fr\u00e5gor\r\n\u00c4ndra en bokning av ett boende som v\u00e4rd\r\nDu kan skicka en \u00e4ndringsf\u00f6rfr\u00e5gan till din g\u00e4st. Om g\u00e4sten godk\u00e4nner s\u00e5 uppdateras bokningen.\r\nL\u00e4s vidare\r\nV\u00e4rdavbokningspolicy f\u00f6r boenden\r\nEffective date: October 9, 2023\r\nL\u00e4s vidare\r\nD\u00e5 f\u00e5r du din utbetalning\r\nVi skickar vanligtvis utbetalningar ungef\u00e4r 24 timmar efter det att g\u00e4sten checkar in f\u00f6r vistelser i boendet och efter det att en tj\u00e4nst eller upplevelse har slutf\u00f6rts. N\u00e4r du f\u00e5r din utbetalning kan variera beroende p\u00e5 flera faktorer.\r\nL\u00e4s vidare\r\nVisa fler \u00e4mnen\r\n",
        "name": "Charlotte S\u00f6derberg",
        "guests": "4 g\u00e4ster",
        "dates": "16\u201318 juli",
        "duration": "2 n\u00e4tter",
        "price": 1940,
        "rating": "?",
        "language": "",
        "living": "",
        "membertime": "2025",
        "host": ""
    },
    "1418fb94e984-19acc0c41e1b2b5fc3fe47b8c047ccf3@airbnb.com": {
        "updated_at": "2025-05-25 18:24:54",
        "raw": "Hoppa till inneh\u00e5ll\r\nIdag\r\nKalender\r\nAnnonser\r\nMeddelanden\r\n\r\nMeny\r\n\r\n\r\n\r\nBokningsinformation\r\nSkriv ut\r\nBekr\u00e4ftad\r\nJohanna Ryderling\r\nProfilbilden f\u00f6r Johanna\r\nStor villa med pool\r\n27\u201329 aug. (2 n\u00e4tter)\r\n6 g\u00e4ster \u00b7 6 660,48 kr\r\nOm Johanna\r\n5,0 i betyg fr\u00e5n 1 omd\u00f6me\r\nIdentitet verifierad\r\nBlev medlem p\u00e5 Airbnb 2024\r\nVisa profil\r\nSkicka eller beg\u00e4r pengar\r\nSkicka meddelande\r\nRing\r\nTelefon: \u202a+46 70 287 54 08\u202c\r\nBokningsinformation\r\nG\u00e4ster\r\n6 vuxna\r\nVisa\r\nIncheckning\r\nons 27 aug. 2025\r\nUtcheckning\r\nfre 29 aug. 2025\r\nBokningsdatum\r\nm\u00e5n 28 apr. 2025\r\nBekr\u00e4ftelsekod\r\nHMA4YR8TQE\r\nAvbokningspolicy\r\nFlexibel\r\nVisa kalender\r\nG\u00e4st betalade\r\nBoende\r\n4 920,00 kr\r\nSt\u00e4davgift\r\n2 000,00 kr\r\nServiceavgift f\u00f6r g\u00e4ster\r\n1 319,89 kr\r\nTotalt (SEK)\r\n8 239,89 kr\r\nUtbetalning f\u00f6r v\u00e4rdar\r\nTotalpris f\u00f6r vistelse\r\n4 920,00 kr\r\nSt\u00e4davgift\r\n2 000,00 kr\r\nServiceavgift f\u00f6r v\u00e4rdar (3.0 % + moms)\r\n\u2212259,52 kr\r\nTotalt (SEK)\r\n6 660,48 kr\r\nMomsfaktura *1407\r\nTransaktionshistorik\r\nKalenderanteckning\r\nL\u00e4gg till en privat p\u00e5minnelse f\u00f6r dessa datum som bara du kan se\r\nSkriv en anteckning\r\nSpara\r\nSkydd fr\u00e5n b\u00f6rjan till slut, varje g\u00e5ng du \u00e4r v\u00e4rd.\r\nL\u00e4s mer\r\nSt\u00f6d\r\n\u00c4ndra bokning\r\nAnm\u00e4l denna g\u00e4st\r\nBes\u00f6k hj\u00e4lpcentret\r\nAnnullera bokning\r\nOm du avbokar kan du komma att debiteras en avgift och dessa datum kan komma att blockeras. Om du avbokar f\u00f6r ofta kan det leda till att du inte \u00e4r ber\u00e4ttigad till Superhost-status och att din annons tillf\u00e4lligt kan st\u00e4ngas av eller tas bort. \r\n\r\nL\u00e4s mer om att avboka\r\nVanliga fr\u00e5gor\r\n\u00c4ndra en bokning av ett boende som v\u00e4rd\r\nDu kan skicka en \u00e4ndringsf\u00f6rfr\u00e5gan till din g\u00e4st. Om g\u00e4sten godk\u00e4nner s\u00e5 uppdateras bokningen.\r\nL\u00e4s vidare\r\nV\u00e4rdavbokningspolicy f\u00f6r boenden\r\nEffective date: October 9, 2023\r\nL\u00e4s vidare\r\nD\u00e5 f\u00e5r du din utbetalning\r\nVi skickar vanligtvis utbetalningar ungef\u00e4r 24 timmar efter det att g\u00e4sten checkar in f\u00f6r vistelser i boendet och efter det att en tj\u00e4nst eller upplevelse har slutf\u00f6rts. N\u00e4r du f\u00e5r din utbetalning kan variera beroende p\u00e5 flera faktorer.\r\nL\u00e4s vidare\r\nVisa fler \u00e4mnen\r\n",
        "name": "Johanna Ryderling",
        "guests": "6 g\u00e4ster",
        "dates": "27\u201329 aug.",
        "duration": "2 n\u00e4tter",
        "price": 6660.48,
        "rating": "5,0",
        "language": "",
        "living": "",
        "membertime": "2024",
        "host": ""
    },
    "1418fb94e984-c5e367a7911af9ea56d9a23efd543719@airbnb.com": {
        "updated_at": "2025-05-25 18:22:53",
        "raw": "Hoppa till inneh\u00e5ll\r\nIdag\r\nKalender\r\nAnnonser\r\nMeddelanden\r\n\r\nMeny\r\n\r\n\r\n\r\nBokningsinformation\r\nSkriv ut\r\nBekr\u00e4ftad\r\nClaes Gartner\r\nProfilbilden f\u00f6r Claes\r\nStor villa med pool\r\n3\u201317 aug. (14 n\u00e4tter)\r\n5 g\u00e4ster \u00b7 30 909,53 kr\r\nOm Claes\r\n4,8 i betyg fr\u00e5n 9 omd\u00f6men\r\nIdentitet verifierad\r\nOcks\u00e5 en v\u00e4rd\r\nBlev medlem p\u00e5 Airbnb 2013\r\nBor i Gen\u00e8ve, Schweiz\r\nTalar engelska, franska och svenska\r\nVisa profil\r\nSkicka eller beg\u00e4r pengar\r\nSkicka meddelande\r\nRing\r\nTelefon: \u202a+41 79 251 51 26\u202c\r\nBokningsinformation\r\nG\u00e4ster\r\n3 vuxna, 2 barn\r\nVisa\r\nIncheckning\r\ns\u00f6n 3 aug. 2025\r\nUtcheckning\r\ns\u00f6n 17 aug. 2025\r\nBokningsdatum\r\nl\u00f6r 19 apr. 2025\r\nBekr\u00e4ftelsekod\r\nHMS23JXF88\r\nAvbokningspolicy\r\nFlexibel\r\nVisa kalender\r\nG\u00e4st betalade\r\n2 151,00 kr x 14 n\u00e4tter\r\n30 114,00 kr\r\nSt\u00e4davgift\r\n2 000,00 kr\r\nServiceavgift f\u00f6r g\u00e4ster\r\n5 297,47 kr\r\nTotalt (SEK)\r\n37 411,47 kr\r\nUtbetalning f\u00f6r v\u00e4rdar\r\nRumsavgift f\u00f6r 14 n\u00e4tter\r\n33 460,00 kr\r\nVisa \u00f6versikt\r\nSt\u00e4davgift\r\n2 000,00 kr\r\nJustering av pris per natt\r\n\u22123 346,00 kr\r\nVisa \u00f6versikt\r\nServiceavgift f\u00f6r v\u00e4rdar (3.0 % + moms)\r\n\u22121 204,47 kr\r\nTotalt (SEK)\r\n30 909,53 kr\r\nMomsfaktura *3240\r\nTransaktionshistorik\r\nKalenderanteckning\r\nL\u00e4gg till en privat p\u00e5minnelse f\u00f6r dessa datum som bara du kan se\r\nSkriv en anteckning\r\nSpara\r\nSkydd fr\u00e5n b\u00f6rjan till slut, varje g\u00e5ng du \u00e4r v\u00e4rd.\r\nL\u00e4s mer\r\nSt\u00f6d\r\n\u00c4ndra bokning\r\nAnm\u00e4l denna g\u00e4st\r\nBes\u00f6k hj\u00e4lpcentret\r\nAnnullera bokning\r\nOm du avbokar kan du komma att debiteras en avgift och dessa datum kan komma att blockeras. Om du avbokar f\u00f6r ofta kan det leda till att du inte \u00e4r ber\u00e4ttigad till Superhost-status och att din annons tillf\u00e4lligt kan st\u00e4ngas av eller tas bort. \r\n\r\nL\u00e4s mer om att avboka\r\nVanliga fr\u00e5gor\r\n\u00c4ndra en bokning av ett boende som v\u00e4rd\r\nDu kan skicka en \u00e4ndringsf\u00f6rfr\u00e5gan till din g\u00e4st. Om g\u00e4sten godk\u00e4nner s\u00e5 uppdateras bokningen.\r\nL\u00e4s vidare\r\nV\u00e4rdavbokningspolicy f\u00f6r boenden\r\nEffective date: October 9, 2023\r\nL\u00e4s vidare\r\nD\u00e5 f\u00e5r du din utbetalning\r\nVi skickar vanligtvis utbetalningar ungef\u00e4r 24 timmar efter det att g\u00e4sten checkar in f\u00f6r vistelser i boendet och efter det att en tj\u00e4nst eller upplevelse har slutf\u00f6rts. N\u00e4r du f\u00e5r din utbetalning kan variera beroende p\u00e5 flera faktorer.\r\nL\u00e4s vidare\r\nVisa fler \u00e4mnen\r\n",
        "name": "Claes Gartner",
        "guests": "5 g\u00e4ster",
        "dates": "3\u201317 aug.",
        "duration": "14 n\u00e4tter",
        "price": 30909.53,
        "rating": "4,8",
        "language": "engelska, franska och svenska",
        "living": "Gen\u00e8ve, Schweiz",
        "membertime": "2013",
        "host": "Ocks\u00e5 en v\u00e4rd"
    },
    "1418fb94e984-fc6282c6dd0e4d7bf71099ad32939af8@airbnb.com": {
        "updated_at": "2025-05-25 18:49:24",
        "raw": "Hoppa till inneh\u00e5ll\r\nIdag\r\nKalender\r\nAnnonser\r\nMeddelanden\r\n\r\nMeny\r\n\r\n\r\n\r\nBokningsinformation\r\nSkriv ut\r\nBekr\u00e4ftad\r\nChristoffer Cavalli-Bj\u00f6rkman\r\nProfilbilden f\u00f6r Christoffer\r\nMysigt boende med egen tomt\r\n18 juli\u2009\u2013\u20091 aug. (14 n\u00e4tter)\r\n2 g\u00e4ster, 1 sp\u00e4dbarn \u00b7 13 440,32 kr\r\nOm Christoffer\r\n4,8 i betyg fr\u00e5n 21 omd\u00f6men\r\nIdentitet verifierad\r\nBlev medlem p\u00e5 Airbnb 2016\r\nBor i Stockholm, Sverige\r\nTalar engelska och svenska\r\nVisa profil\r\nSkicka eller beg\u00e4r pengar\r\nSkicka meddelande\r\nRing\r\nTelefon: \u202a+46 76 165 93 56\u202c\r\nBokningsinformation\r\nG\u00e4ster\r\n2 vuxna, 1 sp\u00e4dbarn\r\nVisa\r\nIncheckning\r\nfre 18 juli 2025\r\nUtcheckning\r\nfre 1 aug. 2025\r\nBokningsdatum\r\ntis 1 apr. 2025\r\nBekr\u00e4ftelsekod\r\nHM5JKCDZET\r\nAvbokningspolicy\r\nFlexibel\r\nVisa kalender\r\nG\u00e4st betalade\r\n989,71 kr x 14 n\u00e4tter\r\n13 856,00 kr\r\nServiceavgift f\u00f6r g\u00e4ster\r\n2 445,19 kr\r\nTotalt (SEK)\r\n16 301,19 kr\r\nUtbetalning f\u00f6r v\u00e4rdar\r\nRumsavgift f\u00f6r 14 n\u00e4tter\r\n17 320,00 kr\r\nVisa \u00f6versikt\r\nJustering av pris per natt\r\n\u22123 464,00 kr\r\nVisa \u00f6versikt\r\nServiceavgift f\u00f6r v\u00e4rdar (3.0 %)\r\n\u2212415,68 kr\r\nTotalt (SEK)\r\n13 440,32 kr\r\nMomsfaktura *4941\r\nTransaktionshistorik\r\nKalenderanteckning\r\nL\u00e4gg till en privat p\u00e5minnelse f\u00f6r dessa datum som bara du kan se\r\nSkriv en anteckning\r\nSpara\r\nSkydd fr\u00e5n b\u00f6rjan till slut, varje g\u00e5ng du \u00e4r v\u00e4rd.\r\nL\u00e4s mer\r\nSt\u00f6d\r\n\u00c4ndra bokning\r\nAnm\u00e4l denna g\u00e4st\r\nBes\u00f6k hj\u00e4lpcentret\r\nAnnullera bokning\r\nOm du avbokar kan du komma att debiteras en avgift och dessa datum kan komma att blockeras. Om du avbokar f\u00f6r ofta kan det leda till att du inte \u00e4r ber\u00e4ttigad till Superhost-status och att din annons tillf\u00e4lligt kan st\u00e4ngas av eller tas bort. \r\n\r\nL\u00e4s mer om att avboka\r\nVanliga fr\u00e5gor\r\n\u00c4ndra en bokning av ett boende som v\u00e4rd\r\nDu kan skicka en \u00e4ndringsf\u00f6rfr\u00e5gan till din g\u00e4st. Om g\u00e4sten godk\u00e4nner s\u00e5 uppdateras bokningen.\r\nL\u00e4s vidare\r\nV\u00e4rdavbokningspolicy f\u00f6r boenden\r\nEffective date: October 9, 2023\r\nL\u00e4s vidare\r\nD\u00e5 f\u00e5r du din utbetalning\r\nVi skickar vanligtvis utbetalningar ungef\u00e4r 24 timmar efter det att g\u00e4sten checkar in f\u00f6r vistelser i boendet och efter det att en tj\u00e4nst eller upplevelse har slutf\u00f6rts. N\u00e4r du f\u00e5r din utbetalning kan variera beroende p\u00e5 flera faktorer.\r\nL\u00e4s vidare\r\nVisa fler \u00e4mnen\r\n",
        "name": "Christoffer Cavalli-Bj\u00f6rkman",
        "guests": "2 g\u00e4ster",
        "dates": "18 juli\u2009\u2013\u20091 aug.",
        "duration": "14 n\u00e4tter",
        "price": 13440.32,
        "rating": "4,8",
        "language": "engelska och svenska",
        "living": "Stockholm, Sverige",
        "membertime": "2016",
        "host": ""
    },
    "1418fb94e984-1a4d299b90a019c2872bb457bff932da@airbnb.com": {
        "updated_at": "2025-05-25 18:34:08",
        "raw": "Hoppa till inneh\u00e5ll\r\nIdag\r\nKalender\r\nAnnonser\r\nMeddelanden\r\n\r\nMeny\r\n\r\n\r\n\r\nBokningsinformation\r\nSkriv ut\r\nBekr\u00e4ftad\r\nIngvar Nilsen\r\nProfilbilden f\u00f6r Ingvar\r\nStor villa med pool\r\n21\u201325 juli (4 n\u00e4tter)\r\n5 g\u00e4ster \u00b7 12 608,75 kr\r\nOm Ingvar\r\n5,0 i betyg fr\u00e5n 2 omd\u00f6men\r\nIdentitet verifierad\r\nBlev medlem p\u00e5 Airbnb 2015\r\nBor i Trondheim, Norge\r\nTalar engelska och norska\r\nVisa profil\r\nSkicka eller beg\u00e4r pengar\r\nSkicka meddelande\r\nRing\r\nTelefon: \u202a+47 95 05 06 60\u202c\r\nBokningsinformation\r\nG\u00e4ster\r\n4 vuxna, 1 barn\r\nVisa\r\nIncheckning\r\nm\u00e5n 21 juli 2025\r\nUtcheckning\r\nfre 25 juli 2025\r\nBokningsdatum\r\nl\u00f6r 5 apr. 2025\r\nBekr\u00e4ftelsekod\r\nHM2Y8T3KBP\r\nAvbokningspolicy\r\nFlexibel\r\nVisa kalender\r\nG\u00e4st betalade\r\n3 275,00 kr x 4 n\u00e4tter\r\n13 100,00 kr\r\nServiceavgift f\u00f6r g\u00e4ster\r\n2 498,63 kr\r\nTotalt (SEK)\r\n15 598,63 kr\r\nUtbetalning f\u00f6r v\u00e4rdar\r\nRumsavgift f\u00f6r 4 n\u00e4tter\r\n13 100,00 kr\r\nVisa \u00f6versikt\r\nServiceavgift f\u00f6r v\u00e4rdar (3.0 % + moms)\r\n\u2212491,25 kr\r\nTotalt (SEK)\r\n12 608,75 kr\r\nMomsfaktura *8292\r\nTransaktionshistorik\r\nKalenderanteckning\r\nL\u00e4gg till en privat p\u00e5minnelse f\u00f6r dessa datum som bara du kan se\r\nSkriv en anteckning\r\nSpara\r\nSkydd fr\u00e5n b\u00f6rjan till slut, varje g\u00e5ng du \u00e4r v\u00e4rd.\r\nL\u00e4s mer\r\nSt\u00f6d\r\n\u00c4ndra bokning\r\nAnm\u00e4l denna g\u00e4st\r\nBes\u00f6k hj\u00e4lpcentret\r\nAnnullera bokning\r\nOm du avbokar kan du komma att debiteras en avgift och dessa datum kan komma att blockeras. Om du avbokar f\u00f6r ofta kan det leda till att du inte \u00e4r ber\u00e4ttigad till Superhost-status och att din annons tillf\u00e4lligt kan st\u00e4ngas av eller tas bort. \r\n\r\nL\u00e4s mer om att avboka\r\nVanliga fr\u00e5gor\r\n\u00c4ndra en bokning av ett boende som v\u00e4rd\r\nDu kan skicka en \u00e4ndringsf\u00f6rfr\u00e5gan till din g\u00e4st. Om g\u00e4sten godk\u00e4nner s\u00e5 uppdateras bokningen.\r\nL\u00e4s vidare\r\nV\u00e4rdavbokningspolicy f\u00f6r boenden\r\nEffective date: October 9, 2023\r\nL\u00e4s vidare\r\nD\u00e5 f\u00e5r du din utbetalning\r\nVi skickar vanligtvis utbetalningar ungef\u00e4r 24 timmar efter det att g\u00e4sten checkar in f\u00f6r vistelser i boendet och efter det att en tj\u00e4nst eller upplevelse har slutf\u00f6rts. N\u00e4r du f\u00e5r din utbetalning kan variera beroende p\u00e5 flera faktorer.\r\nL\u00e4s vidare\r\nVisa fler \u00e4mnen\r\n",
        "name": "Ingvar Nilsen",
        "guests": "5 g\u00e4ster",
        "dates": "21\u201325 juli",
        "duration": "4 n\u00e4tter",
        "price": 12608.75,
        "rating": "5,0",
        "language": "engelska och norska",
        "living": "Trondheim, Norge",
        "membertime": "2015",
        "host": ""
    },
    "1418fb94e984-1e9f9625db11145b4ebe8bd1610e338c@airbnb.com": {
        "updated_at": "2025-05-25 18:49:15",
        "raw": "Hoppa till inneh\u00e5ll\r\nIdag\r\nKalender\r\nAnnonser\r\nMeddelanden\r\n\r\nMeny\r\n\r\n\r\n\r\nBokningsinformation\r\nSkriv ut\r\nBekr\u00e4ftad\r\nSusanne Wollard\r\nProfilbilden f\u00f6r Susanne\r\nStor villa med pool\r\n26 juli\u2009\u2013\u20092 aug. (7 n\u00e4tter)\r\n4 g\u00e4ster \u00b7 13 958,75 kr\r\nOm Susanne\r\nIdentitet verifierad\r\n2 resor\r\nInga omd\u00f6men \u00e4nnu\r\nBlev medlem p\u00e5 Airbnb 2021\r\nVisa profil\r\nSkicka eller beg\u00e4r pengar\r\nSkicka meddelande\r\nRing\r\nTelefon: \u202a+46 70 367 14 09\u202c\r\nBokningsinformation\r\nG\u00e4ster\r\n2 vuxna, 2 barn\r\nVisa\r\nIncheckning\r\nl\u00f6r 26 juli 2025\r\nUtcheckning\r\nl\u00f6r 2 aug. 2025\r\nBokningsdatum\r\nons 16 apr. 2025\r\nBekr\u00e4ftelsekod\r\nHMJK54SCKP\r\nAvbokningspolicy\r\nFlexibel\r\nVisa kalender\r\nG\u00e4st betalade\r\n2 071,80 kr x 7 n\u00e4tter\r\n14 502,60 kr\r\nServiceavgift f\u00f6r g\u00e4ster\r\n2 559,29 kr\r\nTotalt (SEK)\r\n17 061,89 kr\r\nUtbetalning f\u00f6r v\u00e4rdar\r\nRumsavgift f\u00f6r 7 n\u00e4tter\r\n16 114,00 kr\r\nVisa \u00f6versikt\r\nJustering av pris per natt\r\n\u22121 611,40 kr\r\nVisa \u00f6versikt\r\nServiceavgift f\u00f6r v\u00e4rdar (3.0 % + moms)\r\n\u2212543,85 kr\r\nTotalt (SEK)\r\n13 958,75 kr\r\nMomsfaktura *0101\r\nTransaktionshistorik\r\nKalenderanteckning\r\nL\u00e4gg till en privat p\u00e5minnelse f\u00f6r dessa datum som bara du kan se\r\nSkriv en anteckning\r\nSpara\r\nSkydd fr\u00e5n b\u00f6rjan till slut, varje g\u00e5ng du \u00e4r v\u00e4rd.\r\nL\u00e4s mer\r\nSt\u00f6d\r\n\u00c4ndra bokning\r\nAnm\u00e4l denna g\u00e4st\r\nBes\u00f6k hj\u00e4lpcentret\r\nAnnullera bokning\r\nOm du avbokar kan du komma att debiteras en avgift och dessa datum kan komma att blockeras. Om du avbokar f\u00f6r ofta kan det leda till att du inte \u00e4r ber\u00e4ttigad till Superhost-status och att din annons tillf\u00e4lligt kan st\u00e4ngas av eller tas bort. \r\n\r\nL\u00e4s mer om att avboka\r\nVanliga fr\u00e5gor\r\n\u00c4ndra en bokning av ett boende som v\u00e4rd\r\nDu kan skicka en \u00e4ndringsf\u00f6rfr\u00e5gan till din g\u00e4st. Om g\u00e4sten godk\u00e4nner s\u00e5 uppdateras bokningen.\r\nL\u00e4s vidare\r\nV\u00e4rdavbokningspolicy f\u00f6r boenden\r\nEffective date: October 9, 2023\r\nL\u00e4s vidare\r\nD\u00e5 f\u00e5r du din utbetalning\r\nVi skickar vanligtvis utbetalningar ungef\u00e4r 24 timmar efter det att g\u00e4sten checkar in f\u00f6r vistelser i boendet och efter det att en tj\u00e4nst eller upplevelse har slutf\u00f6rts. N\u00e4r du f\u00e5r din utbetalning kan variera beroende p\u00e5 flera faktorer.\r\nL\u00e4s vidare\r\nVisa fler \u00e4mnen\r\n",
        "name": "Susanne Wollard",
        "guests": "4 g\u00e4ster",
        "dates": "26 juli\u2009\u2013\u20092 aug.",
        "duration": "7 n\u00e4tter",
        "price": 13958.75,
        "rating": "?",
        "language": "",
        "living": "",
        "membertime": "2021",
        "host": ""
    },
    "1418fb94e984-6cb4085a41a2072fc5ae9ee1313f5e6e@airbnb.com": {
        "updated_at": "2025-05-25 18:34:56",
        "raw": "Hoppa till inneh\u00e5ll\r\nIdag\r\nKalender\r\nAnnonser\r\nMeddelanden\r\n\r\nMeny\r\n\r\n\r\n\r\nBokningsinformation\r\nSkriv ut\r\nBekr\u00e4ftad\r\nEva Bystedt\r\nProfilbilden f\u00f6r Eva\r\nMysigt boende med egen tomt\r\n1\u201315 aug. (14 n\u00e4tter)\r\n4 g\u00e4ster \u00b7 14 635,36 kr\r\nOm Eva\r\n5,0 i betyg fr\u00e5n 6 omd\u00f6men\r\nIdentitet verifierad\r\nBlev medlem p\u00e5 Airbnb 2018\r\nBor i Solna, Sverige\r\nVisa profil\r\nSkicka eller beg\u00e4r pengar\r\nSkicka meddelande\r\nRing\r\nTelefon: \u202a+46 70 274 60 92\u202c\r\nBokningsinformation\r\nG\u00e4ster\r\n4 vuxna\r\nVisa\r\nIncheckning\r\nfre 1 aug. 2025\r\nUtcheckning\r\nfre 15 aug. 2025\r\nBokningsdatum\r\ntis 1 apr. 2025\r\nBekr\u00e4ftelsekod\r\nHMPPE34KJK\r\nAvbokningspolicy\r\nFlexibel\r\nVisa kalender\r\nG\u00e4st betalade\r\n1 077,71 kr x 14 n\u00e4tter\r\n15 088,00 kr\r\nServiceavgift f\u00f6r g\u00e4ster\r\n2 662,60 kr\r\nTotalt (SEK)\r\n17 750,60 kr\r\nUtbetalning f\u00f6r v\u00e4rdar\r\nRumsavgift f\u00f6r 14 n\u00e4tter\r\n18 860,00 kr\r\nVisa \u00f6versikt\r\nJustering av pris per natt\r\n\u22123 772,00 kr\r\nVisa \u00f6versikt\r\nServiceavgift f\u00f6r v\u00e4rdar (3.0 %)\r\n\u2212452,64 kr\r\nTotalt (SEK)\r\n14 635,36 kr\r\nMomsfaktura *6222\r\nTransaktionshistorik\r\nKalenderanteckning\r\nL\u00e4gg till en privat p\u00e5minnelse f\u00f6r dessa datum som bara du kan se\r\nSkriv en anteckning\r\nSpara\r\nSkydd fr\u00e5n b\u00f6rjan till slut, varje g\u00e5ng du \u00e4r v\u00e4rd.\r\nL\u00e4s mer\r\nSt\u00f6d\r\n\u00c4ndra bokning\r\nAnm\u00e4l denna g\u00e4st\r\nBes\u00f6k hj\u00e4lpcentret\r\nAnnullera bokning\r\nOm du avbokar kan du komma att debiteras en avgift och dessa datum kan komma att blockeras. Om du avbokar f\u00f6r ofta kan det leda till att du inte \u00e4r ber\u00e4ttigad till Superhost-status och att din annons tillf\u00e4lligt kan st\u00e4ngas av eller tas bort. \r\n\r\nL\u00e4s mer om att avboka\r\nVanliga fr\u00e5gor\r\n\u00c4ndra en bokning av ett boende som v\u00e4rd\r\nDu kan skicka en \u00e4ndringsf\u00f6rfr\u00e5gan till din g\u00e4st. Om g\u00e4sten godk\u00e4nner s\u00e5 uppdateras bokningen.\r\nL\u00e4s vidare\r\nV\u00e4rdavbokningspolicy f\u00f6r boenden\r\nEffective date: October 9, 2023\r\nL\u00e4s vidare\r\nD\u00e5 f\u00e5r du din utbetalning\r\nVi skickar vanligtvis utbetalningar ungef\u00e4r 24 timmar efter det att g\u00e4sten checkar in f\u00f6r vistelser i boendet och efter det att en tj\u00e4nst eller upplevelse har slutf\u00f6rts. N\u00e4r du f\u00e5r din utbetalning kan variera beroende p\u00e5 flera faktorer.\r\nL\u00e4s vidare\r\nVisa fler \u00e4mnen\r\n",
        "name": "Eva Bystedt",
        "guests": "4 g\u00e4ster",
        "dates": "1\u201315 aug.",
        "duration": "14 n\u00e4tter",
        "price": 14635.36,
        "rating": "5,0",
        "language": "",
        "living": "Solna, Sverige",
        "membertime": "2018",
        "host": ""
    },
    "1418fb94e984-02624e476c80dc9f4042884a590488be@airbnb.com": {
        "updated_at": "2025-05-30 20:42:02",
        "raw": "Hoppa till inneh\u00e5ll\r\nIdag\r\nKalender\r\nAnnonser\r\nMeddelanden\r\n\r\nMeny\r\n\r\n\r\n\r\nBokningsinformation\r\nSkriv ut\r\nBekr\u00e4ftad\r\nDalius Mazaliauskas\r\nProfilbilden f\u00f6r Dalius\r\nMysigt boende med egen tomt\r\n20\u201321 juni (1 natt)\r\n4 g\u00e4ster \u00b7 970,00 kr\r\nOm Dalius\r\nIdentitet verifierad\r\nInga resor \u00e4nnu\r\nBlev medlem p\u00e5 Airbnb 2024\r\nVisa profil\r\nSkicka eller beg\u00e4r pengar\r\nSkicka meddelande\r\nRing\r\nTelefon: \u202a+46 76 280 16 09\u202c\r\nBokningsinformation\r\nG\u00e4ster\r\n3 vuxna, 1 barn\r\nVisa\r\nIncheckning\r\nfre 20 juni 2025\r\nUtcheckning\r\nl\u00f6r 21 juni 2025\r\nBokningsdatum\r\nfre 30 maj 2025\r\nBekr\u00e4ftelsekod\r\nHM2TTNWMNS\r\nAvbokningspolicy\r\nFlexibel\r\nVisa kalender\r\nG\u00e4st betalade\r\n1 000,00 kr x 1 natt\r\n1 000,00 kr\r\nServiceavgift f\u00f6r g\u00e4ster\r\n176,47 kr\r\nTotalt (SEK)\r\n1 176,47 kr\r\nUtbetalning f\u00f6r v\u00e4rdar\r\nRumsavgift f\u00f6r 1 natt\r\n1 000,00 kr\r\nVisa \u00f6versikt\r\nServiceavgift f\u00f6r v\u00e4rdar (3.0 %)\r\n\u221230,00 kr\r\nTotalt (SEK)\r\n970,00 kr\r\nMomsfaktura *0348\r\nTransaktionshistorik\r\nKalenderanteckning\r\nL\u00e4gg till en privat p\u00e5minnelse f\u00f6r dessa datum som bara du kan se\r\nSkriv en anteckning\r\nSpara\r\nSkydd fr\u00e5n b\u00f6rjan till slut, varje g\u00e5ng du \u00e4r v\u00e4rd.\r\nL\u00e4s mer\r\nSt\u00f6d\r\n\u00c4ndra bokning\r\nAnm\u00e4l denna g\u00e4st\r\nBes\u00f6k hj\u00e4lpcentret\r\nAnnullera bokning\r\nOm du avbokar kan du komma att debiteras en avgift och dessa datum kan komma att blockeras. Om du avbokar f\u00f6r ofta kan det leda till att du inte \u00e4r ber\u00e4ttigad till Superhost-status och att din annons tillf\u00e4lligt kan st\u00e4ngas av eller tas bort. \r\n\r\nL\u00e4s mer om att avboka\r\nVanliga fr\u00e5gor\r\n\u00c4ndra en bokning av ett boende som v\u00e4rd\r\nDu kan skicka en \u00e4ndringsf\u00f6rfr\u00e5gan till din g\u00e4st. Om g\u00e4sten godk\u00e4nner s\u00e5 uppdateras bokningen.\r\nL\u00e4s vidare\r\nV\u00e4rdavbokningspolicy f\u00f6r boenden\r\nEffective date: October 9, 2023\r\nL\u00e4s vidare\r\nD\u00e5 f\u00e5r du din utbetalning\r\nVi skickar vanligtvis utbetalningar ungef\u00e4r 24 timmar efter det att g\u00e4sten checkar in f\u00f6r vistelser i boendet och efter det att en tj\u00e4nst eller upplevelse har slutf\u00f6rts. N\u00e4r du f\u00e5r din utbetalning kan variera beroende p\u00e5 flera faktorer.\r\nL\u00e4s vidare\r\nVisa fler \u00e4mnen\r\n",
        "name": "Dalius Mazaliauskas",
        "guests": "4 g\u00e4ster",
        "dates": "20\u201321 juni",
        "duration": "1 natt",
        "price": 970,
        "rating": "?",
        "language": "",
        "living": "",
        "membertime": "2024",
        "host": ""
    },
    "1418fb94e984-acb9e23f88a9d9f814406598be374f8f@airbnb.com": {
        "updated_at": "2025-06-10 11:14:30",
        "raw": "Hoppa till inneh\u00e5ll\r\nIdag\r\nKalender\r\nAnnonser\r\nMeddelanden\r\n\r\nMeny\r\n\r\n\r\n\r\nBokningsinformation\r\nSkriv ut\r\nBekr\u00e4ftad\r\nJonas Gabot\r\nProfilbilden f\u00f6r Jonas\r\nStor villa med pool\r\n12\u201314 sep. (2 n\u00e4tter)\r\n6 g\u00e4ster \u00b7 6 356,35 kr\r\nOm Jonas\r\nIdentitet verifierad\r\nInga resor \u00e4nnu\r\nBlev medlem p\u00e5 Airbnb 2025\r\nVisa profil\r\nSkicka eller beg\u00e4r pengar\r\nSkicka meddelande\r\nRing\r\nTelefon: \u202a+46 70 202 12 14\u202c\r\nBokningsinformation\r\nG\u00e4ster\r\n6 vuxna\r\nVisa\r\nIncheckning\r\nfre 12 sep. 2025\r\nUtcheckning\r\ns\u00f6n 14 sep. 2025\r\nBokningsdatum\r\nfre 6 juni 2025\r\nBekr\u00e4ftelsekod\r\nHMSRHWMHMD\r\nAvbokningspolicy\r\nFlexibel\r\nVisa kalender\r\nG\u00e4st betalade\r\n2 302,00 kr x 2 n\u00e4tter\r\n4 604,00 kr\r\nSt\u00e4davgift\r\n2 000,00 kr\r\nServiceavgift f\u00f6r g\u00e4ster\r\n1 165,41 kr\r\nTotalt (SEK)\r\n7 769,41 kr\r\nUtbetalning f\u00f6r v\u00e4rdar\r\nRumsavgift f\u00f6r 2 n\u00e4tter\r\n4 604,00 kr\r\nVisa \u00f6versikt\r\nSt\u00e4davgift\r\n2 000,00 kr\r\nServiceavgift f\u00f6r v\u00e4rdar (3.0 % + moms)\r\n\u2212247,65 kr\r\nTotalt (SEK)\r\n6 356,35 kr\r\nMomsfaktura *0601\r\nTransaktionshistorik\r\nKalenderanteckning\r\nL\u00e4gg till en privat p\u00e5minnelse f\u00f6r dessa datum som bara du kan se\r\nSkriv en anteckning\r\nSpara\r\nAirCover f\u00f6r v\u00e4rdar\r\nSkydd fr\u00e5n b\u00f6rjan till slut, varje g\u00e5ng du \u00e4r v\u00e4rd.\r\nL\u00e4s mer\r\nSt\u00f6d\r\n\u00c4ndra bokning\r\nAnm\u00e4l denna g\u00e4st\r\nBes\u00f6k hj\u00e4lpcentret\r\nAnnullera bokning\r\nOm du avbokar kan du komma att debiteras en avgift och dessa datum kan komma att blockeras. Om du avbokar f\u00f6r ofta kan det leda till att du inte \u00e4r ber\u00e4ttigad till Superhost-status och att din annons tillf\u00e4lligt kan st\u00e4ngas av eller tas bort. \r\n\r\nL\u00e4s mer om att avboka\r\nVanliga fr\u00e5gor\r\n\u00c4ndra en bokning av ett boende som v\u00e4rd\r\nDu kan skicka en \u00e4ndringsf\u00f6rfr\u00e5gan till din g\u00e4st. Om g\u00e4sten godk\u00e4nner s\u00e5 uppdateras bokningen.\r\nL\u00e4s vidare\r\nV\u00e4rdavbokningspolicy f\u00f6r boenden\r\nEffective date: October 9, 2023\r\nL\u00e4s vidare\r\nD\u00e5 f\u00e5r du din utbetalning\r\nVi skickar vanligtvis utbetalningar ungef\u00e4r 24 timmar efter det att g\u00e4sten checkar in f\u00f6r vistelser i boendet och efter det att en tj\u00e4nst eller upplevelse har slutf\u00f6rts. N\u00e4r du f\u00e5r din utbetalning kan variera beroende p\u00e5 flera faktorer.\r\nL\u00e4s vidare\r\nVisa fler \u00e4mnen\r\n",
        "name": "Jonas Gabot",
        "guests": "6 g\u00e4ster",
        "dates": "12\u201314 Sep.",
        "duration": "2 n\u00e4tter",
        "price": 6356.35,
        "rating": "?",
        "language": "",
        "living": "",
        "membertime": "2025",
        "host": ""
    },
    "1418fb94e984-722bf94f4dbac38e440d94fd558cec85@airbnb.com": {
        "updated_at": "2025-06-28 13:29:12",
        "raw": "Hoppa till inneh\u00e5ll\r\nIdag\r\nKalender\r\nAnnonser\r\nMeddelanden\r\n\r\nMeny\r\n\r\n2\r\n\r\n\r\nBokningsinformation\r\nSkriv ut\r\nBekr\u00e4ftad\r\nMaria Syrrist\r\nProfilbilden f\u00f6r Maria\r\nMysigt boende med egen tomt\r\n17\u201324 aug. (7 n\u00e4tter)\r\n3 g\u00e4ster \u00b7 10 621,50 kr\r\nOm Maria\r\n5,0 i betyg fr\u00e5n 4 omd\u00f6men\r\nIdentitet verifierad\r\nOcks\u00e5 en v\u00e4rd\r\nBlev medlem p\u00e5 Airbnb 2016\r\nBor i London, Storbritannien\r\nTalar engelska och svenska\r\nVisa profil\r\nSkicka eller beg\u00e4r pengar\r\nSkicka meddelande\r\nRing\r\nTelefon: \u202a+44 7745 960052\u202c\r\nBokningsinformation\r\nG\u00e4ster\r\n1 vuxen, 2 barn\r\nVisa\r\nIncheckning\r\ns\u00f6n 17 aug. 2025\r\nUtcheckning\r\ns\u00f6n 24 aug. 2025\r\nBokningsdatum\r\ns\u00f6n 22 juni 2025\r\nBekr\u00e4ftelsekod\r\nHMZEF9DC2N\r\nAvbokningspolicy\r\nFlexibel\r\nVisa kalender\r\nG\u00e4st betalade\r\n1 350,00 kr x 7 n\u00e4tter\r\n9 450,00 kr\r\nSt\u00e4davgift\r\n1 500,00 kr\r\nServiceavgift f\u00f6r g\u00e4ster\r\n2 005,01 kr\r\nTotalt (SEK)\r\n12 955,01 kr\r\nUtbetalning f\u00f6r v\u00e4rdar\r\nRumsavgift f\u00f6r 7 n\u00e4tter\r\n10 500,00 kr\r\nVisa \u00f6versikt\r\nSt\u00e4davgift\r\n1 500,00 kr\r\nJustering av pris per natt\r\n\u22121 050,00 kr\r\nVisa \u00f6versikt\r\nServiceavgift f\u00f6r v\u00e4rdar (3.0 %)\r\n\u2212328,50 kr\r\nTotalt (SEK)\r\n10 621,50 kr\r\nMomsfaktura *6191\r\nTransaktionshistorik\r\nKalenderanteckning\r\nL\u00e4gg till en privat p\u00e5minnelse f\u00f6r dessa datum som bara du kan se\r\nSkriv en anteckning\r\nSpara\r\nSkydd fr\u00e5n b\u00f6rjan till slut, varje g\u00e5ng du \u00e4r v\u00e4rd.\r\nL\u00e4s mer\r\nSt\u00f6d\r\n\u00c4ndra bokning\r\nAnm\u00e4l denna g\u00e4st\r\nBes\u00f6k hj\u00e4lpcentret\r\nAnnullera bokning\r\nOm du avbokar kan du komma att debiteras en avgift och dessa datum kan komma att blockeras. Om du avbokar f\u00f6r ofta kan det leda till att du inte \u00e4r ber\u00e4ttigad till Superhost-status och att din annons tillf\u00e4lligt kan st\u00e4ngas av eller tas bort. \r\n\r\nL\u00e4s mer om att avboka\r\nVanliga fr\u00e5gor\r\n\u00c4ndra en bokning av ett boende som v\u00e4rd\r\nDu kan skicka en \u00e4ndringsf\u00f6rfr\u00e5gan till din g\u00e4st. Om g\u00e4sten godk\u00e4nner s\u00e5 uppdateras bokningen.\r\nL\u00e4s vidare\r\nV\u00e4rdavbokningspolicy f\u00f6r boenden\r\nEffective date: October 9, 2023\r\nL\u00e4s vidare\r\nD\u00e5 f\u00e5r du din utbetalning\r\nVi skickar vanligtvis utbetalningar ungef\u00e4r 24 timmar efter det att g\u00e4sten checkar in f\u00f6r vistelser i boendet och efter det att en tj\u00e4nst eller upplevelse har slutf\u00f6rts. N\u00e4r du f\u00e5r din utbetalning kan variera beroende p\u00e5 flera faktorer.\r\nL\u00e4s vidare\r\nVisa fler \u00e4mnen\r\n",
        "name": "Maria Syrrist",
        "guests": "3 g\u00e4ster",
        "dates": "17\u201324 Aug.",
        "duration": "7 n\u00e4tter",
        "price": 10621.5,
        "rating": "5,0",
        "language": "engelska och svenska",
        "living": "London, Storbritannien",
        "membertime": "2016",
        "host": "Ocks\u00e5 en v\u00e4rd"
    },
    "1418fb94e984-89d005f9cffa08f2c46f64581e619456@airbnb.com": {
        "updated_at": "2025-08-06 14:42:27",
        "raw": "Hoppa till inneh\u00e5ll\r\nIdag\r\nKalender\r\nAnnonser\r\nMeddelanden\r\n\r\nMeny\r\n\r\n\r\n\r\nBokningsinformation\r\nSkriv ut\r\nV\u00e4rd f\u00f6r n\u00e4rvarande\r\nJohnny Hallberg\r\nProfilbilden f\u00f6r Johnny\r\nStor villa med pool\r\n4\u20139 aug. (5 n\u00e4tter)\r\n6 g\u00e4ster \u00b7 13 090,00 kr\r\nOm Johnny\r\nIdentitet verifierad\r\nInga resor \u00e4nnu\r\nBlev medlem p\u00e5 Airbnb 2025\r\nVisa profil\r\nSkicka eller beg\u00e4r pengar\r\nSkicka meddelande\r\nRing\r\nTelefon: \u202a+46 70 690 19 39\u202c\r\nBokningsinformation\r\nG\u00e4ster\r\n5 vuxna, 1 barn\r\nVisa\r\nIncheckning\r\nm\u00e5n 4 aug. 2025\r\nUtcheckning\r\nl\u00f6r 9 aug. 2025\r\nBokningsdatum\r\nl\u00f6r 12 juli 2025\r\nBekr\u00e4ftelsekod\r\nHM32PBRCAS\r\nAvbokningspolicy\r\nFlexibel\r\nVisa kalender\r\nG\u00e4st betalade\r\n2 320,00 kr x 5 n\u00e4tter\r\n11 600,00 kr\r\nSt\u00e4davgift\r\n2 000,00 kr\r\nServiceavgift f\u00f6r g\u00e4ster\r\n2 400,01 kr\r\nTotalt (SEK)\r\n16 000,01 kr\r\nUtbetalning f\u00f6r v\u00e4rdar\r\nRumsavgift f\u00f6r 5 n\u00e4tter\r\n11 600,00 kr\r\nVisa \u00f6versikt\r\nSt\u00e4davgift\r\n2 000,00 kr\r\nServiceavgift f\u00f6r v\u00e4rdar (3.0 % + moms)\r\n\u2212510,00 kr\r\nTotalt (SEK)\r\n13 090,00 kr\r\nMomsfaktura *4598\r\nTransaktionshistorik\r\nKalenderanteckning\r\nL\u00e4gg till en privat p\u00e5minnelse f\u00f6r dessa datum som bara du kan se\r\nSkriv en anteckning\r\nSpara\r\nSkydd fr\u00e5n b\u00f6rjan till slut, varje g\u00e5ng du \u00e4r v\u00e4rd.\r\nL\u00e4s mer\r\nSt\u00f6d\r\n\u00c4ndra bokning\r\nHj\u00e4lp med ett s\u00e4kerhetsproblem\r\nBes\u00f6k hj\u00e4lpcentret\r\nAnnullera bokning\r\nOm du avbokar kan du komma att debiteras en avgift och dessa datum kan komma att blockeras. Om du avbokar f\u00f6r ofta kan det leda till att du inte \u00e4r ber\u00e4ttigad till Superhost-status och att din annons tillf\u00e4lligt kan st\u00e4ngas av eller tas bort. \r\n\r\nL\u00e4s mer om att avboka\r\nVanliga fr\u00e5gor\r\n\u00c4ndra en bokning av ett boende som v\u00e4rd\r\nDu kan skicka en \u00e4ndringsf\u00f6rfr\u00e5gan till din g\u00e4st. Om g\u00e4sten godk\u00e4nner s\u00e5 uppdateras bokningen.\r\nL\u00e4s vidare\r\nN\u00e4r en g\u00e4st inte dyker upp p\u00e5 sin bokning\r\nOm din g\u00e4st avbokar eller inte dyker upp kommer vi att uppr\u00e4tth\u00e5lla din avbokningspolicy och eventuell utbetalning kommer att skickas till dig.\r\nL\u00e4s vidare\r\nOm en g\u00e4st f\u00e5r dig att k\u00e4nna dig illa till mods\r\nOm du uppt\u00e4cker att en g\u00e4st bryter mot n\u00e5gon av dina husregler eller har f\u00e5tt dig att k\u00e4nna dig otrygg kan du alltid avb\u00f6ja resef\u00f6rfr\u00e5gan eller avboka bokningen.\r\nL\u00e4s vidare\r\nVisa fler \u00e4mnen\r\n",
        "guests": "6 g\u00e4ster",
        "dates": "4\u20139 Aug.",
        "duration": "5 n\u00e4tter",
        "price": 13090,
        "rating": "?",
        "language": "",
        "living": "",
        "membertime": "2025",
        "host": ""
    },
    "1418fb94e984-1d0a431191bf018bc690b6358046bd59@airbnb.com": {
        "updated_at": "2025-08-06 14:42:55",
        "raw": "Hoppa till inneh\u00e5ll\r\nIdag\r\nKalender\r\nAnnonser\r\nMeddelanden\r\n\r\nMeny\r\n\r\n\r\n\r\nBokningsinformation\r\nSkriv ut\r\nBekr\u00e4ftad\r\nLinn Hjertstedt\r\nProfilbilden f\u00f6r Linn\r\nStor villa med pool\r\n10\u201313 aug. (3 n\u00e4tter)\r\n6 g\u00e4ster \u00b7 6 737,50 kr\r\nOm Linn\r\nIdentitet verifierad\r\nInga resor \u00e4nnu\r\nBlev medlem p\u00e5 Airbnb 2025\r\nVisa profil\r\nSkicka eller beg\u00e4r pengar\r\nSkicka meddelande\r\nRing\r\nTelefon: \u202a+46 70 278 74 72\u202c\r\nBokningsinformation\r\nG\u00e4ster\r\n3 vuxna, 3 barn\r\nVisa\r\nIncheckning\r\ns\u00f6n 10 aug. 2025\r\nUtcheckning\r\nons 13 aug. 2025\r\nBokningsdatum\r\ntors 17 juli 2025\r\nBekr\u00e4ftelsekod\r\nHMN3RRFAZM\r\nAvbokningspolicy\r\nFlexibel\r\nVisa kalender\r\nG\u00e4st betalade\r\nBoende\r\n5 000,00 kr\r\nSt\u00e4davgift\r\n2 000,00 kr\r\nServiceavgift f\u00f6r g\u00e4ster\r\n1 235,30 kr\r\nTotalt (SEK)\r\n8 235,30 kr\r\nUtbetalning f\u00f6r v\u00e4rdar\r\nTotalpris f\u00f6r vistelse\r\n5 000,00 kr\r\nSt\u00e4davgift\r\n2 000,00 kr\r\nServiceavgift f\u00f6r v\u00e4rdar (3.0 % + moms)\r\n\u2212262,50 kr\r\nTotalt (SEK)\r\n6 737,50 kr\r\nMomsfaktura *4107\r\nTransaktionshistorik\r\nKalenderanteckning\r\nL\u00e4gg till en privat p\u00e5minnelse f\u00f6r dessa datum som bara du kan se\r\nSkriv en anteckning\r\nSpara\r\nSkydd fr\u00e5n b\u00f6rjan till slut, varje g\u00e5ng du \u00e4r v\u00e4rd.\r\nL\u00e4s mer\r\nSt\u00f6d\r\n\u00c4ndra bokning\r\nAnm\u00e4l denna g\u00e4st\r\nBes\u00f6k hj\u00e4lpcentret\r\nAnnullera bokning\r\nOm du avbokar kan du komma att debiteras en avgift och dessa datum kan komma att blockeras. Om du avbokar f\u00f6r ofta kan det leda till att du inte \u00e4r ber\u00e4ttigad till Superhost-status och att din annons tillf\u00e4lligt kan st\u00e4ngas av eller tas bort. \r\n\r\nL\u00e4s mer om att avboka\r\nVanliga fr\u00e5gor\r\n\u00c4ndra en bokning av ett boende som v\u00e4rd\r\nDu kan skicka en \u00e4ndringsf\u00f6rfr\u00e5gan till din g\u00e4st. Om g\u00e4sten godk\u00e4nner s\u00e5 uppdateras bokningen.\r\nL\u00e4s vidare\r\nV\u00e4rdavbokningspolicy f\u00f6r boenden\r\nEffective date: October 9, 2023\r\nL\u00e4s vidare\r\nD\u00e5 f\u00e5r du din utbetalning\r\nVi skickar vanligtvis utbetalningar ungef\u00e4r 24 timmar efter det att g\u00e4sten checkar in f\u00f6r vistelser i boendet och efter det att en tj\u00e4nst eller upplevelse har slutf\u00f6rts. N\u00e4r du f\u00e5r din utbetalning kan variera beroende p\u00e5 flera faktorer.\r\nL\u00e4s vidare\r\nVisa fler \u00e4mnen\r\n",
        "name": "Linn Hjertstedt",
        "guests": "6 g\u00e4ster",
        "dates": "10\u201313 Aug.",
        "duration": "3 n\u00e4tter",
        "price": 6737.5,
        "rating": "?",
        "language": "",
        "living": "",
        "membertime": "2025",
        "host": ""
    },
    "1418fb94e984-ec0d3203b0d5e5c73fbc6138528f901d@airbnb.com": {
        "updated_at": "2025-08-06 14:43:16",
        "raw": "Hoppa till inneh\u00e5ll\r\nIdag\r\nKalender\r\nAnnonser\r\nMeddelanden\r\n\r\nMeny\r\n\r\n\r\n\r\nBokningsinformation\r\nSkriv ut\r\nBekr\u00e4ftad\r\nCatarina Lindqvist Ryan\r\nProfilbilden f\u00f6r Catarina\r\nStor villa med pool\r\n14\u201318 aug. (4 n\u00e4tter)\r\n4 g\u00e4ster \u00b7 10 818,55 kr\r\nOm Catarina\r\n5,0 i betyg fr\u00e5n 2 omd\u00f6men\r\nIdentitet verifierad\r\nBlev medlem p\u00e5 Airbnb 2019\r\nBor i New Jersey, USA\r\nVisa profil\r\nSkicka eller beg\u00e4r pengar\r\nSkicka meddelande\r\nRing\r\nTelefon: \u202a+1 908-902-8847\u202c\r\nBokningsinformation\r\nG\u00e4ster\r\n4 vuxna\r\nVisa\r\nIncheckning\r\ntors 14 aug. 2025\r\nUtcheckning\r\nm\u00e5n 18 aug. 2025\r\nBokningsdatum\r\nl\u00f6r 26 juli 2025\r\nBekr\u00e4ftelsekod\r\nHMRXYHYFY9\r\nAvbokningspolicy\r\nFlexibel\r\nVisa kalender\r\nG\u00e4st betalade\r\n2 310,00 kr x 4 n\u00e4tter\r\n9 240,00 kr\r\nSt\u00e4davgift\r\n2 000,00 kr\r\nServiceavgift f\u00f6r g\u00e4ster\r\n1 715,10 kr\r\nTotalt (SEK)\r\n12 955,10 kr\r\nUtbetalning f\u00f6r v\u00e4rdar\r\nRumsavgift f\u00f6r 4 n\u00e4tter\r\n9 240,00 kr\r\nVisa \u00f6versikt\r\nSt\u00e4davgift\r\n2 000,00 kr\r\nServiceavgift f\u00f6r v\u00e4rdar (3.0 % + moms)\r\n\u2212421,45 kr\r\nTotalt (SEK)\r\n10 818,55 kr\r\nMomsfaktura *9332\r\nTransaktionshistorik\r\nKalenderanteckning\r\nL\u00e4gg till en privat p\u00e5minnelse f\u00f6r dessa datum som bara du kan se\r\nSkriv en anteckning\r\nSpara\r\nSkydd fr\u00e5n b\u00f6rjan till slut, varje g\u00e5ng du \u00e4r v\u00e4rd.\r\nL\u00e4s mer\r\nSt\u00f6d\r\n\u00c4ndra bokning\r\nAnm\u00e4l denna g\u00e4st\r\nBes\u00f6k hj\u00e4lpcentret\r\nAnnullera bokning\r\nOm du avbokar kan du komma att debiteras en avgift och dessa datum kan komma att blockeras. Om du avbokar f\u00f6r ofta kan det leda till att du inte \u00e4r ber\u00e4ttigad till Superhost-status och att din annons tillf\u00e4lligt kan st\u00e4ngas av eller tas bort. \r\n\r\nL\u00e4s mer om att avboka\r\nVanliga fr\u00e5gor\r\n\u00c4ndra en bokning av ett boende som v\u00e4rd\r\nDu kan skicka en \u00e4ndringsf\u00f6rfr\u00e5gan till din g\u00e4st. Om g\u00e4sten godk\u00e4nner s\u00e5 uppdateras bokningen.\r\nL\u00e4s vidare\r\nV\u00e4rdavbokningspolicy f\u00f6r boenden\r\nEffective date: October 9, 2023\r\nL\u00e4s vidare\r\nD\u00e5 f\u00e5r du din utbetalning\r\nVi skickar vanligtvis utbetalningar ungef\u00e4r 24 timmar efter det att g\u00e4sten checkar in f\u00f6r vistelser i boendet och efter det att en tj\u00e4nst eller upplevelse har slutf\u00f6rts. N\u00e4r du f\u00e5r din utbetalning kan variera beroende p\u00e5 flera faktorer.\r\nL\u00e4s vidare\r\nVisa fler \u00e4mnen\r\n",
        "name": "Catarina Lindqvist Ryan",
        "guests": "4 g\u00e4ster",
        "dates": "14\u201318 Aug.",
        "duration": "4 n\u00e4tter",
        "price": 10818.55,
        "rating": "5,0",
        "language": "",
        "living": "New Jersey, USA",
        "membertime": "2019",
        "host": ""
    },
    "1418fb94e984-21f48e4330b6e4f52a9adb034a738b4a@airbnb.com": {
        "updated_at": "2025-08-06 16:54:03",
        "raw": "Hoppa till inneh\u00e5ll\r\nIdag\r\nKalender\r\nAnnonser\r\nMeddelanden\r\n\r\nMeny\r\n\r\n\r\n\r\nBokningsinformation\r\nSkriv ut\r\nBekr\u00e4ftad\r\nGertrud Fecher\r\nProfilbilden f\u00f6r Gertrud\r\nStor villa med pool\r\n20\u201326 aug. (6 n\u00e4tter)\r\n3 g\u00e4ster \u00b7 15 265,23 kr\r\nOm Gertrud\r\n5,0 i betyg fr\u00e5n 1 omd\u00f6me\r\nIdentitet verifierad\r\nBlev medlem p\u00e5 Airbnb 2023\r\nVisa profil\r\nSkicka eller beg\u00e4r pengar\r\nSkicka meddelande\r\nRing\r\nTelefon: \u202a+49 1575 2139348\u202c\r\nBokningsinformation\r\nG\u00e4ster\r\n3 vuxna\r\nVisa\r\nIncheckning\r\nons 20 aug. 2025\r\nUtcheckning\r\ntis 26 aug. 2025\r\nBokningsdatum\r\nm\u00e5n 14 juli 2025\r\nBekr\u00e4ftelsekod\r\nHMQ2P4MTRQ\r\nAvbokningspolicy\r\nFlexibel\r\nVisa kalender\r\nG\u00e4st betalade\r\n2 310,00 kr x 6 n\u00e4tter\r\n13 860,00 kr\r\nSt\u00e4davgift\r\n2 000,00 kr\r\nServiceavgift f\u00f6r g\u00e4ster\r\n2 879,86 kr\r\nTotalt (SEK)\r\n18 739,86 kr\r\nUtbetalning f\u00f6r v\u00e4rdar\r\nRumsavgift f\u00f6r 6 n\u00e4tter\r\n13 860,00 kr\r\nVisa \u00f6versikt\r\nSt\u00e4davgift\r\n2 000,00 kr\r\nServiceavgift f\u00f6r v\u00e4rdar (3.0 % + moms)\r\n\u2212594,77 kr\r\nTotalt (SEK)\r\n15 265,23 kr\r\nMomsfaktura *6388\r\nTransaktionshistorik\r\nKalenderanteckning\r\nL\u00e4gg till en privat p\u00e5minnelse f\u00f6r dessa datum som bara du kan se\r\nSkriv en anteckning\r\nSpara\r\nSkydd fr\u00e5n b\u00f6rjan till slut, varje g\u00e5ng du \u00e4r v\u00e4rd.\r\nL\u00e4s mer\r\nSt\u00f6d\r\n\u00c4ndra bokning\r\nAnm\u00e4l denna g\u00e4st\r\nBes\u00f6k hj\u00e4lpcentret\r\nAnnullera bokning\r\nOm du avbokar kan du komma att debiteras en avgift och dessa datum kan komma att blockeras. Om du avbokar f\u00f6r ofta kan det leda till att du inte \u00e4r ber\u00e4ttigad till Superhost-status och att din annons tillf\u00e4lligt kan st\u00e4ngas av eller tas bort. \r\n\r\nL\u00e4s mer om att avboka\r\nVanliga fr\u00e5gor\r\n\u00c4ndra en bokning av ett boende som v\u00e4rd\r\nDu kan skicka en \u00e4ndringsf\u00f6rfr\u00e5gan till din g\u00e4st. Om g\u00e4sten godk\u00e4nner s\u00e5 uppdateras bokningen.\r\nL\u00e4s vidare\r\nV\u00e4rdavbokningspolicy f\u00f6r boenden\r\nEffective date: October 9, 2023\r\nL\u00e4s vidare\r\nD\u00e5 f\u00e5r du din utbetalning\r\nVi skickar vanligtvis utbetalningar ungef\u00e4r 24 timmar efter det att g\u00e4sten checkar in f\u00f6r vistelser i boendet och efter det att en tj\u00e4nst eller upplevelse har slutf\u00f6rts. N\u00e4r du f\u00e5r din utbetalning kan variera beroende p\u00e5 flera faktorer.\r\nL\u00e4s vidare\r\nVisa fler \u00e4mnen\r\n",
        "name": "Gertrud Fecher",
        "guests": "3 g\u00e4ster",
        "dates": "20\u201326 Aug.",
        "duration": "6 n\u00e4tter",
        "price": 15265.23,
        "rating": "5,0",
        "language": "",
        "living": "",
        "membertime": "2023",
        "host": ""
    }
}